deathstar/__init__.py
deathstar-0.1.0.dist-info/METADATA
deathstar-0.1.0.dist-info/WHEEL
deathstar-0.1.0.dist-info/top_level.txt
deathstar-0.1.0.dist-info/RECORD
