Metadata-Version: 2.1
Name: deathstar
Version: 0.1.0
Summary: Destroy Stuff
Home-page: https://repl.it/@rediar/Deathstar-py-package
Author: rediar
Author-email: placeholder@example.com
License: UNKNOWN
Platform: UNKNOWN
Classifier: Programming Language :: Python :: 3
Classifier: License :: OSI Approved :: MIT License
Classifier: Operating System :: OS Independent
Requires-Python: >=3.6
